Metadata-Version: 2.1
Name: mockry
Version: 0.0.3
Summary: mockry - A rich mock server you have searched for
Home-page: https://github.com/glibin/mockry
License: LICENSE
Download-URL: https://github.com/glibin/mockry/tarball/0.0.3
Platform: UNKNOWN
Classifier: License :: OSI Approved :: MIT License
Classifier: Programming Language :: Python
Classifier: Programming Language :: Python :: 3.7
Requires-Python: >= 3.7
